setup.py
distributions_999/Binomialdistribution.py
distributions_999/Gaussiandistribution.py
distributions_999/Generaldistribution.py
distributions_999/__init__.py
distributions_999.egg-info/PKG-INFO
distributions_999.egg-info/SOURCES.txt
distributions_999.egg-info/dependency_links.txt
distributions_999.egg-info/not-zip-safe
distributions_999.egg-info/top_level.txt