Metadata-Version: 1.0
Name: distributions-999
Version: 0.1
Summary: Gaussian and Binomial distributions
Home-page: UNKNOWN
Author: Muhsin Sahin
Author-email: sahinmuhsin2018@gmail.com
License: UNKNOWN
Platform: UNKNOWN
